acs_download/__init__.py
acs_download/acs_download.py
acs_download/cli.py
acs_download/download.py
acs_download/url_builder.py
acs_download-0.1.5.dist-info/AUTHORS.rst
acs_download-0.1.5.dist-info/LICENSE
acs_download-0.1.5.dist-info/METADATA
acs_download-0.1.5.dist-info/WHEEL
acs_download-0.1.5.dist-info/entry_points.txt
acs_download-0.1.5.dist-info/top_level.txt
acs_download-0.1.5.dist-info/RECORD
