Metadata-Version: 2.1
Name: acs-download
Version: 0.1.5
Summary: Download American Community Survey (ACS) complete Public Use Micro Sample (PUMS) data files from census FTP server.
Home-page: https://github.com/chekos/acs_download
Author: Sergio Sánchez Zavala
Author-email: sergio@cimarron.io
License: MIT license
Keywords: acs_download
Platform: UNKNOWN
Classifier: Development Status :: 2 - Pre-Alpha
Classifier: Intended Audience :: Developers
Classifier: License :: OSI Approved :: MIT License
Classifier: Natural Language :: English
Classifier: Programming Language :: Python :: 3.6
Classifier: Programming Language :: Python :: 3.7
Requires-Dist: Click (>=6.0)
Requires-Dist: us (>=1.0)
Requires-Dist: tqdm (>=4.31)
Requires-Dist: requests (>=2.21)
